topsis/__init__.py
topsis/topsis.py
Topsis_Harinderjit_102017151-1.0.6.dist-info/METADATA
Topsis_Harinderjit_102017151-1.0.6.dist-info/WHEEL
Topsis_Harinderjit_102017151-1.0.6.dist-info/entry_points.txt
Topsis_Harinderjit_102017151-1.0.6.dist-info/top_level.txt
Topsis_Harinderjit_102017151-1.0.6.dist-info/RECORD
