Metadata-Version: 2.1
Name: Topsis-Harinderjit-102017151
Version: 1.0.6
Summary: topsis package for MCDM problems
Author: Harinderjit Singh
Author-email: harinderjit91218@gmail.com
Classifier: Programming Language :: Python :: 3
Classifier: Programming Language :: Python :: 3.6
Classifier: Programming Language :: Python :: 3.7
Classifier: License :: OSI Approved :: MIT License
Classifier: Operating System :: OS Independent
Requires-Python: >=3.6
Requires-Dist: pandas
